sinch_spectre-0.1.30.data/scripts/spectre
spectre/__init__.py
spectre/__main__.py
spectre/config.py
spectre/creator.py
spectre/model.py
spectre/serializer.py
spectre/utils.py
spectre/generation/__init__.py
spectre/generation/api_json.py
spectre/generation/generator.py
spectre/generation/java.py
spectre/generation/jhipster.py
spectre/generation/kotlin.py
spectre/generation/liquibase.py
spectre/generation/proto.py
spectre/generation/templates/__init__.py
spectre/generation/templates/api_json_template.py
spectre/importers/__init__.py
spectre/importers/mysql.py
sinch_spectre-0.1.30.dist-info/LICENSE
sinch_spectre-0.1.30.dist-info/METADATA
sinch_spectre-0.1.30.dist-info/WHEEL
sinch_spectre-0.1.30.dist-info/top_level.txt
sinch_spectre-0.1.30.dist-info/RECORD
