Metadata-Version: 2.1
Name: sinch-spectre
Version: 0.1.30
Summary: CLI tool for generating API specification from a generic data model.
Home-page: https://www.git.clxnetworks.net/routing/spectre
Author: Sinch Routing Team
Author-email: max.forsman@sinch.com
License: UNKNOWN
Platform: UNKNOWN
Classifier: Programming Language :: Python :: 3
Classifier: License :: OSI Approved :: MIT License
Classifier: Operating System :: OS Independent
Requires-Python: >=3.7
Requires-Dist: click
Requires-Dist: pyyaml
